[
    {
        "start": "0:00:01.184000",
        "end": "0:00:01.792000",
        "speaker": "1"
    },
    {
        "start": "0:00:03.872000",
        "end": "0:00:04.448000",
        "speaker": "1"
    },
    {
        "start": "0:00:05.632000",
        "end": "0:00:07.200000",
        "speaker": "1"
    },
    {
        "start": "0:00:08.096000",
        "end": "0:00:09.056000",
        "speaker": "1"
    },
    {
        "start": "0:00:09.120000",
        "end": "0:00:09.664000",
        "speaker": "1"
    },
    {
        "start": "0:00:10.176000",
        "end": "0:00:10.880000",
        "speaker": "1"
    },
    {
        "start": "0:00:12.128000",
        "end": "0:00:12.768000",
        "speaker": "1"
    },
    {
        "start": "0:00:12.832000",
        "end": "0:00:13.376000",
        "speaker": "1"
    },
    {
        "start": "0:00:13.696000",
        "end": "0:00:14.240000",
        "speaker": "1"
    },
    {
        "start": "0:00:15.584000",
        "end": "0:00:16.096000",
        "speaker": "1"
    },
    {
        "start": "0:00:16.864000",
        "end": "0:00:17.440000",
        "speaker": "1"
    },
    {
        "start": "0:00:20.160000",
        "end": "0:00:21.088000",
        "speaker": "1"
    },
    {
        "start": "0:00:24.192000",
        "end": "0:00:24.800000",
        "speaker": "1"
    },
    {
        "start": "0:00:25.760000",
        "end": "0:00:26.464000",
        "speaker": "1"
    },
    {
        "start": "0:00:29.888000",
        "end": "0:00:30.720000",
        "speaker": "1"
    },
    {
        "start": "0:00:31.616000",
        "end": "0:00:32.512000",
        "speaker": "1"
    },
    {
        "start": "0:00:32.640000",
        "end": "0:00:33.664000",
        "speaker": "1"
    },
    {
        "start": "0:00:36.544000",
        "end": "0:00:37.120000",
        "speaker": "1"
    },
    {
        "start": "0:00:37.472000",
        "end": "0:00:38.368000",
        "speaker": "1"
    },
    {
        "start": "0:00:39.904000",
        "end": "0:00:40.960000",
        "speaker": "1"
    },
    {
        "start": "0:00:41.440000",
        "end": "0:00:42.144000",
        "speaker": "1"
    },
    {
        "start": "0:00:42.176000",
        "end": "0:00:43.104000",
        "speaker": "1"
    },
    {
        "start": "0:00:44.448000",
        "end": "0:00:45.824000",
        "speaker": "1"
    },
    {
        "start": "0:00:47.296000",
        "end": "0:00:49.024000",
        "speaker": "1"
    },
    {
        "start": "0:00:50.304000",
        "end": "0:00:51.424000",
        "speaker": "1"
    },
    {
        "start": "0:00:52.256000",
        "end": "0:00:52.960000",
        "speaker": "1"
    },
    {
        "start": "0:00:53.536000",
        "end": "0:00:54.144000",
        "speaker": "1"
    },
    {
        "start": "0:00:54.528000",
        "end": "0:00:55.104000",
        "speaker": "1"
    },
    {
        "start": "0:00:55.136000",
        "end": "0:00:56.352000",
        "speaker": "1"
    },
    {
        "start": "0:00:56.864000",
        "end": "0:00:58.560000",
        "speaker": "1"
    },
    {
        "start": "0:01:00.384000",
        "end": "0:01:01.536000",
        "speaker": "1"
    },
    {
        "start": "0:01:01.568000",
        "end": "0:01:02.080000",
        "speaker": "1"
    },
    {
        "start": "0:01:02.432000",
        "end": "0:01:02.976000",
        "speaker": "1"
    },
    {
        "start": "0:01:03.040000",
        "end": "0:01:04.416000",
        "speaker": "1"
    },
    {
        "start": "0:01:05.184000",
        "end": "0:01:06.112000",
        "speaker": "1"
    },
    {
        "start": "0:01:08.384000",
        "end": "0:01:09.280000",
        "speaker": "1"
    },
    {
        "start": "0:01:10.112000",
        "end": "0:01:10.688000",
        "speaker": "1"
    },
    {
        "start": "0:01:16.512000",
        "end": "0:01:18.432000",
        "speaker": "1"
    },
    {
        "start": "0:01:18.560000",
        "end": "0:01:19.136000",
        "speaker": "1"
    },
    {
        "start": "0:01:20",
        "end": "0:01:20.544000",
        "speaker": "1"
    },
    {
        "start": "0:01:21.408000",
        "end": "0:01:22.144000",
        "speaker": "1"
    },
    {
        "start": "0:01:22.272000",
        "end": "0:01:22.784000",
        "speaker": "1"
    },
    {
        "start": "0:01:25.504000",
        "end": "0:01:26.528000",
        "speaker": "1"
    },
    {
        "start": "0:01:28.800000",
        "end": "0:01:29.728000",
        "speaker": "1"
    },
    {
        "start": "0:01:31.968000",
        "end": "0:01:32.704000",
        "speaker": "1"
    },
    {
        "start": "0:01:33.600000",
        "end": "0:01:34.400000",
        "speaker": "1"
    },
    {
        "start": "0:01:34.816000",
        "end": "0:01:35.552000",
        "speaker": "1"
    },
    {
        "start": "0:01:36",
        "end": "0:01:36.704000",
        "speaker": "1"
    },
    {
        "start": "0:01:38.720000",
        "end": "0:01:39.360000",
        "speaker": "1"
    },
    {
        "start": "0:01:40.096000",
        "end": "0:01:40.768000",
        "speaker": "1"
    },
    {
        "start": "0:01:40.896000",
        "end": "0:01:41.792000",
        "speaker": "1"
    },
    {
        "start": "0:01:44.640000",
        "end": "0:01:45.824000",
        "speaker": "1"
    },
    {
        "start": "0:01:46.624000",
        "end": "0:01:47.424000",
        "speaker": "1"
    },
    {
        "start": "0:01:48.992000",
        "end": "0:01:49.632000",
        "speaker": "1"
    },
    {
        "start": "0:01:55.040000",
        "end": "0:01:55.872000",
        "speaker": "1"
    },
    {
        "start": "0:01:56.032000",
        "end": "0:01:57.120000",
        "speaker": "1"
    },
    {
        "start": "0:01:58.112000",
        "end": "0:01:58.848000",
        "speaker": "1"
    },
    {
        "start": "0:02:00.608000",
        "end": "0:02:01.600000",
        "speaker": "1"
    },
    {
        "start": "0:02:02.688000",
        "end": "0:02:03.232000",
        "speaker": "1"
    },
    {
        "start": "0:02:03.264000",
        "end": "0:02:04.256000",
        "speaker": "1"
    },
    {
        "start": "0:02:04.288000",
        "end": "0:02:04.864000",
        "speaker": "1"
    },
    {
        "start": "0:02:05.536000",
        "end": "0:02:06.048000",
        "speaker": "1"
    },
    {
        "start": "0:02:06.656000",
        "end": "0:02:07.456000",
        "speaker": "1"
    },
    {
        "start": "0:02:08.896000",
        "end": "0:02:10.176000",
        "speaker": "1"
    },
    {
        "start": "0:02:10.848000",
        "end": "0:02:11.872000",
        "speaker": "1"
    },
    {
        "start": "0:02:12.544000",
        "end": "0:02:13.312000",
        "speaker": "1"
    },
    {
        "start": "0:02:13.376000",
        "end": "0:02:14.080000",
        "speaker": "1"
    },
    {
        "start": "0:02:15.104000",
        "end": "0:02:16.032000",
        "speaker": "1"
    },
    {
        "start": "0:02:17.120000",
        "end": "0:02:17.760000",
        "speaker": "1"
    },
    {
        "start": "0:02:17.792000",
        "end": "0:02:18.624000",
        "speaker": "1"
    },
    {
        "start": "0:02:19.648000",
        "end": "0:02:20.160000",
        "speaker": "1"
    },
    {
        "start": "0:02:21.216000",
        "end": "0:02:21.760000",
        "speaker": "1"
    },
    {
        "start": "0:02:23.168000",
        "end": "0:02:24.416000",
        "speaker": "1"
    },
    {
        "start": "0:02:24.480000",
        "end": "0:02:25.312000",
        "speaker": "1"
    },
    {
        "start": "0:02:25.728000",
        "end": "0:02:26.592000",
        "speaker": "1"
    },
    {
        "start": "0:02:26.784000",
        "end": "0:02:28.448000",
        "speaker": "1"
    },
    {
        "start": "0:02:29.120000",
        "end": "0:02:30.176000",
        "speaker": "1"
    },
    {
        "start": "0:02:30.240000",
        "end": "0:02:30.944000",
        "speaker": "1"
    },
    {
        "start": "0:02:31.328000",
        "end": "0:02:31.872000",
        "speaker": "1"
    },
    {
        "start": "0:02:34.752000",
        "end": "0:02:35.584000",
        "speaker": "1"
    },
    {
        "start": "0:02:35.616000",
        "end": "0:02:36.512000",
        "speaker": "1"
    },
    {
        "start": "0:02:37.856000",
        "end": "0:02:38.816000",
        "speaker": "1"
    },
    {
        "start": "0:02:39.232000",
        "end": "0:02:40.160000",
        "speaker": "1"
    },
    {
        "start": "0:02:42.464000",
        "end": "0:02:43.040000",
        "speaker": "1"
    },
    {
        "start": "0:02:43.936000",
        "end": "0:02:44.480000",
        "speaker": "1"
    },
    {
        "start": "0:02:45.696000",
        "end": "0:02:46.304000",
        "speaker": "1"
    },
    {
        "start": "0:02:46.336000",
        "end": "0:02:47.296000",
        "speaker": "1"
    },
    {
        "start": "0:02:48.576000",
        "end": "0:02:49.344000",
        "speaker": "1"
    },
    {
        "start": "0:02:50.176000",
        "end": "0:02:50.976000",
        "speaker": "1"
    },
    {
        "start": "0:02:53.088000",
        "end": "0:02:54.944000",
        "speaker": "1"
    },
    {
        "start": "0:02:55.008000",
        "end": "0:02:55.904000",
        "speaker": "1"
    },
    {
        "start": "0:02:57.888000",
        "end": "0:02:58.400000",
        "speaker": "1"
    },
    {
        "start": "0:02:58.464000",
        "end": "0:02:59.008000",
        "speaker": "OL"
    },
    {
        "start": "0:03:01.888000",
        "end": "0:03:02.400000",
        "speaker": "1"
    },
    {
        "start": "0:03:03.520000",
        "end": "0:03:05.408000",
        "speaker": "1"
    },
    {
        "start": "0:03:05.472000",
        "end": "0:03:06.336000",
        "speaker": "1"
    },
    {
        "start": "0:03:07.008000",
        "end": "0:03:08",
        "speaker": "1"
    },
    {
        "start": "0:03:08.736000",
        "end": "0:03:09.664000",
        "speaker": "1"
    },
    {
        "start": "0:03:10.784000",
        "end": "0:03:11.840000",
        "speaker": "1"
    },
    {
        "start": "0:03:15.744000",
        "end": "0:03:17.024000",
        "speaker": "1"
    },
    {
        "start": "0:03:17.664000",
        "end": "0:03:18.976000",
        "speaker": "1"
    },
    {
        "start": "0:03:20.352000",
        "end": "0:03:20.928000",
        "speaker": "1"
    },
    {
        "start": "0:03:21.440000",
        "end": "0:03:21.984000",
        "speaker": "1"
    },
    {
        "start": "0:03:22.528000",
        "end": "0:03:23.136000",
        "speaker": "1"
    },
    {
        "start": "0:03:24.736000",
        "end": "0:03:25.344000",
        "speaker": "1"
    },
    {
        "start": "0:03:25.888000",
        "end": "0:03:26.784000",
        "speaker": "1"
    },
    {
        "start": "0:03:28.896000",
        "end": "0:03:29.824000",
        "speaker": "1"
    },
    {
        "start": "0:03:30.784000",
        "end": "0:03:32.160000",
        "speaker": "1"
    },
    {
        "start": "0:03:34.976000",
        "end": "0:03:35.744000",
        "speaker": "1"
    },
    {
        "start": "0:03:36.704000",
        "end": "0:03:37.664000",
        "speaker": "1"
    },
    {
        "start": "0:03:38.816000",
        "end": "0:03:39.744000",
        "speaker": "1"
    },
    {
        "start": "0:03:40.096000",
        "end": "0:03:41.824000",
        "speaker": "1"
    },
    {
        "start": "0:03:42.336000",
        "end": "0:03:43.136000",
        "speaker": "1"
    },
    {
        "start": "0:03:43.648000",
        "end": "0:03:44.480000",
        "speaker": "1"
    },
    {
        "start": "0:03:48.608000",
        "end": "0:03:49.184000",
        "speaker": "1"
    },
    {
        "start": "0:03:49.760000",
        "end": "0:03:50.400000",
        "speaker": "1"
    },
    {
        "start": "0:03:51.808000",
        "end": "0:03:53.632000",
        "speaker": "1"
    },
    {
        "start": "0:03:55.200000",
        "end": "0:03:55.808000",
        "speaker": "1"
    },
    {
        "start": "0:03:58.944000",
        "end": "0:03:59.712000",
        "speaker": "1"
    },
    {
        "start": "0:04:01.760000",
        "end": "0:04:02.464000",
        "speaker": "1"
    },
    {
        "start": "0:04:02.496000",
        "end": "0:04:03.584000",
        "speaker": "1"
    },
    {
        "start": "0:04:03.840000",
        "end": "0:04:04.768000",
        "speaker": "1"
    },
    {
        "start": "0:04:04.864000",
        "end": "0:04:05.376000",
        "speaker": "1"
    },
    {
        "start": "0:04:05.792000",
        "end": "0:04:06.976000",
        "speaker": "1"
    },
    {
        "start": "0:04:07.360000",
        "end": "0:04:09.184000",
        "speaker": "1"
    },
    {
        "start": "0:04:09.568000",
        "end": "0:04:11.072000",
        "speaker": "1"
    },
    {
        "start": "0:04:11.136000",
        "end": "0:04:11.680000",
        "speaker": "1"
    },
    {
        "start": "0:04:12.576000",
        "end": "0:04:13.440000",
        "speaker": "1"
    },
    {
        "start": "0:04:15.584000",
        "end": "0:04:16.128000",
        "speaker": "1"
    },
    {
        "start": "0:04:16.896000",
        "end": "0:04:18.176000",
        "speaker": "1"
    },
    {
        "start": "0:04:18.208000",
        "end": "0:04:18.752000",
        "speaker": "OL"
    },
    {
        "start": "0:04:19.584000",
        "end": "0:04:20.352000",
        "speaker": "1"
    },
    {
        "start": "0:04:21.536000",
        "end": "0:04:22.240000",
        "speaker": "1"
    },
    {
        "start": "0:04:22.432000",
        "end": "0:04:23.328000",
        "speaker": "1"
    },
    {
        "start": "0:04:23.584000",
        "end": "0:04:24.288000",
        "speaker": "1"
    },
    {
        "start": "0:04:24.800000",
        "end": "0:04:25.856000",
        "speaker": "1"
    },
    {
        "start": "0:04:26.208000",
        "end": "0:04:26.880000",
        "speaker": "1"
    },
    {
        "start": "0:04:26.976000",
        "end": "0:04:27.840000",
        "speaker": "1"
    },
    {
        "start": "0:04:29.152000",
        "end": "0:04:29.696000",
        "speaker": "1"
    },
    {
        "start": "0:04:29.888000",
        "end": "0:04:30.656000",
        "speaker": "1"
    },
    {
        "start": "0:04:31.072000",
        "end": "0:04:32.512000",
        "speaker": "1"
    },
    {
        "start": "0:04:34.592000",
        "end": "0:04:35.840000",
        "speaker": "1"
    },
    {
        "start": "0:04:36.448000",
        "end": "0:04:37.728000",
        "speaker": "1"
    },
    {
        "start": "0:04:38.336000",
        "end": "0:04:39.648000",
        "speaker": "1"
    },
    {
        "start": "0:04:39.744000",
        "end": "0:04:41.216000",
        "speaker": "1"
    },
    {
        "start": "0:04:41.728000",
        "end": "0:04:42.368000",
        "speaker": "1"
    },
    {
        "start": "0:04:42.720000",
        "end": "0:04:44.288000",
        "speaker": "1"
    },
    {
        "start": "0:04:44.320000",
        "end": "0:04:45.024000",
        "speaker": "1"
    },
    {
        "start": "0:04:45.632000",
        "end": "0:04:46.368000",
        "speaker": "1"
    },
    {
        "start": "0:04:47.552000",
        "end": "0:04:48.256000",
        "speaker": "1"
    },
    {
        "start": "0:04:48.832000",
        "end": "0:04:49.664000",
        "speaker": "1"
    },
    {
        "start": "0:04:50.048000",
        "end": "0:04:51.392000",
        "speaker": "1"
    },
    {
        "start": "0:04:52.032000",
        "end": "0:04:53.088000",
        "speaker": "1"
    },
    {
        "start": "0:04:53.184000",
        "end": "0:04:53.792000",
        "speaker": "1"
    },
    {
        "start": "0:04:54.144000",
        "end": "0:04:56.096000",
        "speaker": "1"
    },
    {
        "start": "0:04:56.384000",
        "end": "0:04:57.120000",
        "speaker": "1"
    },
    {
        "start": "0:04:57.344000",
        "end": "0:04:58.432000",
        "speaker": "1"
    },
    {
        "start": "0:04:59.232000",
        "end": "0:04:59.904000",
        "speaker": "1"
    },
    {
        "start": "0:05:01.152000",
        "end": "0:05:01.984000",
        "speaker": "1"
    },
    {
        "start": "0:05:02.592000",
        "end": "0:05:03.232000",
        "speaker": "1"
    },
    {
        "start": "0:05:03.584000",
        "end": "0:05:04.416000",
        "speaker": "1"
    },
    {
        "start": "0:05:04.672000",
        "end": "0:05:05.248000",
        "speaker": "1"
    },
    {
        "start": "0:05:05.568000",
        "end": "0:05:06.496000",
        "speaker": "1"
    },
    {
        "start": "0:05:06.880000",
        "end": "0:05:07.840000",
        "speaker": "1"
    },
    {
        "start": "0:05:10.240000",
        "end": "0:05:10.816000",
        "speaker": "1"
    },
    {
        "start": "0:05:11.040000",
        "end": "0:05:11.936000",
        "speaker": "1"
    },
    {
        "start": "0:05:19.392000",
        "end": "0:05:20.288000",
        "speaker": "0"
    },
    {
        "start": "0:05:20.992000",
        "end": "0:05:22.464000",
        "speaker": "0"
    },
    {
        "start": "0:05:22.496000",
        "end": "0:05:23.744000",
        "speaker": "0"
    },
    {
        "start": "0:05:24.512000",
        "end": "0:05:25.088000",
        "speaker": "0"
    },
    {
        "start": "0:05:25.440000",
        "end": "0:05:26.848000",
        "speaker": "0"
    },
    {
        "start": "0:05:26.880000",
        "end": "0:05:27.488000",
        "speaker": "0"
    },
    {
        "start": "0:05:28.256000",
        "end": "0:05:28.832000",
        "speaker": "0"
    },
    {
        "start": "0:05:30.656000",
        "end": "0:05:31.520000",
        "speaker": "0"
    },
    {
        "start": "0:05:35.104000",
        "end": "0:05:35.680000",
        "speaker": "0"
    },
    {
        "start": "0:05:35.776000",
        "end": "0:05:37.440000",
        "speaker": "0"
    },
    {
        "start": "0:05:38.240000",
        "end": "0:05:39.360000",
        "speaker": "0"
    },
    {
        "start": "0:05:39.392000",
        "end": "0:05:40.512000",
        "speaker": "0"
    },
    {
        "start": "0:05:40.896000",
        "end": "0:05:41.760000",
        "speaker": "0"
    },
    {
        "start": "0:05:43.040000",
        "end": "0:05:44.288000",
        "speaker": "0"
    },
    {
        "start": "0:05:44.576000",
        "end": "0:05:45.120000",
        "speaker": "0"
    },
    {
        "start": "0:05:45.408000",
        "end": "0:05:46.560000",
        "speaker": "0"
    },
    {
        "start": "0:05:47.136000",
        "end": "0:05:49.280000",
        "speaker": "0"
    },
    {
        "start": "0:05:50.176000",
        "end": "0:05:50.848000",
        "speaker": "0"
    },
    {
        "start": "0:05:50.944000",
        "end": "0:05:51.648000",
        "speaker": "0"
    },
    {
        "start": "0:05:53.120000",
        "end": "0:05:54.624000",
        "speaker": "0"
    },
    {
        "start": "0:05:54.656000",
        "end": "0:05:55.168000",
        "speaker": "0"
    },
    {
        "start": "0:05:55.232000",
        "end": "0:05:55.936000",
        "speaker": "0"
    },
    {
        "start": "0:05:55.968000",
        "end": "0:05:57.120000",
        "speaker": "0"
    },
    {
        "start": "0:05:58.400000",
        "end": "0:06:01.536000",
        "speaker": "0"
    },
    {
        "start": "0:06:01.568000",
        "end": "0:06:02.624000",
        "speaker": "0"
    },
    {
        "start": "0:06:02.912000",
        "end": "0:06:04.992000",
        "speaker": "0"
    },
    {
        "start": "0:06:05.024000",
        "end": "0:06:06.464000",
        "speaker": "0"
    },
    {
        "start": "0:06:08.032000",
        "end": "0:06:09.056000",
        "speaker": "0"
    },
    {
        "start": "0:06:09.504000",
        "end": "0:06:10.592000",
        "speaker": "0"
    },
    {
        "start": "0:06:11.360000",
        "end": "0:06:12.512000",
        "speaker": "0"
    },
    {
        "start": "0:06:12.608000",
        "end": "0:06:13.600000",
        "speaker": "0"
    },
    {
        "start": "0:06:15.040000",
        "end": "0:06:15.840000",
        "speaker": "0"
    },
    {
        "start": "0:06:16.928000",
        "end": "0:06:18.112000",
        "speaker": "0"
    },
    {
        "start": "0:06:18.656000",
        "end": "0:06:19.712000",
        "speaker": "0"
    },
    {
        "start": "0:06:21.376000",
        "end": "0:06:21.920000",
        "speaker": "0"
    },
    {
        "start": "0:06:23.616000",
        "end": "0:06:24.544000",
        "speaker": "0"
    },
    {
        "start": "0:06:24.992000",
        "end": "0:06:27.232000",
        "speaker": "0"
    },
    {
        "start": "0:06:27.264000",
        "end": "0:06:28.128000",
        "speaker": "0"
    },
    {
        "start": "0:06:29.088000",
        "end": "0:06:30.656000",
        "speaker": "0"
    },
    {
        "start": "0:06:31.168000",
        "end": "0:06:32.992000",
        "speaker": "0"
    },
    {
        "start": "0:06:33.920000",
        "end": "0:06:35.232000",
        "speaker": "0"
    },
    {
        "start": "0:06:37.152000",
        "end": "0:06:38.528000",
        "speaker": "0"
    },
    {
        "start": "0:06:39.712000",
        "end": "0:06:40.640000",
        "speaker": "0"
    },
    {
        "start": "0:06:42.400000",
        "end": "0:06:43.520000",
        "speaker": "0"
    },
    {
        "start": "0:06:43.552000",
        "end": "0:06:44.224000",
        "speaker": "0"
    },
    {
        "start": "0:06:45.152000",
        "end": "0:06:46.688000",
        "speaker": "0"
    },
    {
        "start": "0:06:46.720000",
        "end": "0:06:48.032000",
        "speaker": "0"
    },
    {
        "start": "0:06:49.120000",
        "end": "0:06:50.496000",
        "speaker": "0"
    },
    {
        "start": "0:06:50.592000",
        "end": "0:06:51.456000",
        "speaker": "0"
    },
    {
        "start": "0:06:51.744000",
        "end": "0:06:53.440000",
        "speaker": "0"
    },
    {
        "start": "0:06:58.720000",
        "end": "0:06:59.488000",
        "speaker": "0"
    },
    {
        "start": "0:06:59.520000",
        "end": "0:07:00.160000",
        "speaker": "0"
    },
    {
        "start": "0:07:02.528000",
        "end": "0:07:03.200000",
        "speaker": "0"
    },
    {
        "start": "0:07:03.232000",
        "end": "0:07:04.416000",
        "speaker": "0"
    },
    {
        "start": "0:07:04.448000",
        "end": "0:07:05.216000",
        "speaker": "0"
    },
    {
        "start": "0:07:05.344000",
        "end": "0:07:05.952000",
        "speaker": "0"
    },
    {
        "start": "0:07:06.016000",
        "end": "0:07:07.200000",
        "speaker": "0"
    },
    {
        "start": "0:07:07.264000",
        "end": "0:07:08.096000",
        "speaker": "0"
    },
    {
        "start": "0:07:08.544000",
        "end": "0:07:10.336000",
        "speaker": "0"
    },
    {
        "start": "0:07:10.368000",
        "end": "0:07:11.072000",
        "speaker": "0"
    },
    {
        "start": "0:07:12.896000",
        "end": "0:07:13.792000",
        "speaker": "0"
    },
    {
        "start": "0:07:14.336000",
        "end": "0:07:14.848000",
        "speaker": "0"
    },
    {
        "start": "0:07:16.128000",
        "end": "0:07:16.672000",
        "speaker": "0"
    },
    {
        "start": "0:07:16.768000",
        "end": "0:07:17.376000",
        "speaker": "0"
    },
    {
        "start": "0:07:18.432000",
        "end": "0:07:19.008000",
        "speaker": "0"
    },
    {
        "start": "0:07:19.840000",
        "end": "0:07:20.736000",
        "speaker": "0"
    },
    {
        "start": "0:07:21.376000",
        "end": "0:07:21.952000",
        "speaker": "0"
    },
    {
        "start": "0:07:22.880000",
        "end": "0:07:25.216000",
        "speaker": "0"
    },
    {
        "start": "0:07:26.848000",
        "end": "0:07:27.872000",
        "speaker": "0"
    },
    {
        "start": "0:07:28.960000",
        "end": "0:07:29.504000",
        "speaker": "0"
    },
    {
        "start": "0:07:30.144000",
        "end": "0:07:30.944000",
        "speaker": "0"
    },
    {
        "start": "0:07:33.440000",
        "end": "0:07:34.592000",
        "speaker": "0"
    },
    {
        "start": "0:07:34.624000",
        "end": "0:07:35.872000",
        "speaker": "0"
    },
    {
        "start": "0:07:38.112000",
        "end": "0:07:40.512000",
        "speaker": "0"
    },
    {
        "start": "0:07:41.152000",
        "end": "0:07:41.824000",
        "speaker": "0"
    },
    {
        "start": "0:07:43.136000",
        "end": "0:07:44.384000",
        "speaker": "0"
    },
    {
        "start": "0:07:44.416000",
        "end": "0:07:45.120000",
        "speaker": "0"
    },
    {
        "start": "0:07:45.184000",
        "end": "0:07:45.984000",
        "speaker": "0"
    },
    {
        "start": "0:07:46.144000",
        "end": "0:07:46.656000",
        "speaker": "0"
    },
    {
        "start": "0:07:47.104000",
        "end": "0:07:48.192000",
        "speaker": "0"
    },
    {
        "start": "0:07:49.664000",
        "end": "0:07:50.208000",
        "speaker": "0"
    },
    {
        "start": "0:07:50.240000",
        "end": "0:07:50.944000",
        "speaker": "0"
    },
    {
        "start": "0:07:50.976000",
        "end": "0:07:51.584000",
        "speaker": "0"
    },
    {
        "start": "0:07:53.568000",
        "end": "0:07:54.272000",
        "speaker": "0"
    },
    {
        "start": "0:07:54.912000",
        "end": "0:07:55.648000",
        "speaker": "0"
    },
    {
        "start": "0:07:57.472000",
        "end": "0:07:57.984000",
        "speaker": "0"
    },
    {
        "start": "0:07:58.048000",
        "end": "0:07:58.848000",
        "speaker": "0"
    },
    {
        "start": "0:07:59.488000",
        "end": "0:08:00.064000",
        "speaker": "0"
    },
    {
        "start": "0:08:00.608000",
        "end": "0:08:01.312000",
        "speaker": "0"
    },
    {
        "start": "0:08:01.984000",
        "end": "0:08:02.624000",
        "speaker": "0"
    },
    {
        "start": "0:08:02.656000",
        "end": "0:08:03.616000",
        "speaker": "0"
    },
    {
        "start": "0:08:03.648000",
        "end": "0:08:04.544000",
        "speaker": "0"
    },
    {
        "start": "0:08:04.832000",
        "end": "0:08:05.376000",
        "speaker": "0"
    },
    {
        "start": "0:08:06.240000",
        "end": "0:08:07.104000",
        "speaker": "0"
    },
    {
        "start": "0:08:07.200000",
        "end": "0:08:07.872000",
        "speaker": "0"
    },
    {
        "start": "0:08:08.224000",
        "end": "0:08:09.344000",
        "speaker": "0"
    },
    {
        "start": "0:08:14.880000",
        "end": "0:08:15.776000",
        "speaker": "0"
    },
    {
        "start": "0:08:15.840000",
        "end": "0:08:16.576000",
        "speaker": "0"
    },
    {
        "start": "0:08:17.696000",
        "end": "0:08:18.208000",
        "speaker": "0"
    },
    {
        "start": "0:08:18.400000",
        "end": "0:08:19.552000",
        "speaker": "0"
    },
    {
        "start": "0:08:19.872000",
        "end": "0:08:22.048000",
        "speaker": "0"
    },
    {
        "start": "0:08:23.520000",
        "end": "0:08:25.120000",
        "speaker": "0"
    },
    {
        "start": "0:08:26.272000",
        "end": "0:08:27.456000",
        "speaker": "0"
    },
    {
        "start": "0:08:27.520000",
        "end": "0:08:29.056000",
        "speaker": "0"
    },
    {
        "start": "0:08:30.240000",
        "end": "0:08:30.848000",
        "speaker": "0"
    },
    {
        "start": "0:08:30.880000",
        "end": "0:08:31.808000",
        "speaker": "0"
    },
    {
        "start": "0:08:31.840000",
        "end": "0:08:32.544000",
        "speaker": "0"
    },
    {
        "start": "0:08:33.824000",
        "end": "0:08:35.200000",
        "speaker": "0"
    },
    {
        "start": "0:08:36.736000",
        "end": "0:08:37.312000",
        "speaker": "0"
    },
    {
        "start": "0:08:37.376000",
        "end": "0:08:39.040000",
        "speaker": "0"
    },
    {
        "start": "0:08:39.712000",
        "end": "0:08:40.288000",
        "speaker": "0"
    },
    {
        "start": "0:08:40.320000",
        "end": "0:08:42.016000",
        "speaker": "0"
    },
    {
        "start": "0:08:42.528000",
        "end": "0:08:44",
        "speaker": "0"
    },
    {
        "start": "0:08:46.560000",
        "end": "0:08:49.024000",
        "speaker": "0"
    },
    {
        "start": "0:08:49.664000",
        "end": "0:08:50.560000",
        "speaker": "0"
    },
    {
        "start": "0:08:51.168000",
        "end": "0:08:52.736000",
        "speaker": "0"
    },
    {
        "start": "0:08:53.952000",
        "end": "0:08:55.232000",
        "speaker": "0"
    },
    {
        "start": "0:08:55.648000",
        "end": "0:08:57.536000",
        "speaker": "0"
    },
    {
        "start": "0:09:00.032000",
        "end": "0:09:01.664000",
        "speaker": "0"
    },
    {
        "start": "0:09:03.584000",
        "end": "0:09:04.096000",
        "speaker": "0"
    },
    {
        "start": "0:09:05.152000",
        "end": "0:09:05.760000",
        "speaker": "0"
    },
    {
        "start": "0:09:06.304000",
        "end": "0:09:06.912000",
        "speaker": "0"
    },
    {
        "start": "0:09:09.280000",
        "end": "0:09:10.016000",
        "speaker": "0"
    },
    {
        "start": "0:09:10.304000",
        "end": "0:09:10.848000",
        "speaker": "0"
    },
    {
        "start": "0:09:10.880000",
        "end": "0:09:11.552000",
        "speaker": "0"
    },
    {
        "start": "0:09:12.224000",
        "end": "0:09:14.144000",
        "speaker": "0"
    },
    {
        "start": "0:09:14.816000",
        "end": "0:09:15.328000",
        "speaker": "0"
    },
    {
        "start": "0:09:15.392000",
        "end": "0:09:16.864000",
        "speaker": "0"
    },
    {
        "start": "0:09:17.344000",
        "end": "0:09:18.080000",
        "speaker": "0"
    },
    {
        "start": "0:09:19.072000",
        "end": "0:09:20.128000",
        "speaker": "0"
    },
    {
        "start": "0:09:20.352000",
        "end": "0:09:21.056000",
        "speaker": "0"
    },
    {
        "start": "0:09:22.272000",
        "end": "0:09:22.816000",
        "speaker": "0"
    },
    {
        "start": "0:09:22.976000",
        "end": "0:09:23.584000",
        "speaker": "0"
    },
    {
        "start": "0:09:23.744000",
        "end": "0:09:24.800000",
        "speaker": "0"
    },
    {
        "start": "0:09:25.184000",
        "end": "0:09:25.824000",
        "speaker": "0"
    },
    {
        "start": "0:09:26.208000",
        "end": "0:09:27.520000",
        "speaker": "0"
    },
    {
        "start": "0:09:28.224000",
        "end": "0:09:29.632000",
        "speaker": "0"
    },
    {
        "start": "0:09:31.232000",
        "end": "0:09:32.672000",
        "speaker": "0"
    },
    {
        "start": "0:09:32.704000",
        "end": "0:09:34.496000",
        "speaker": "0"
    },
    {
        "start": "0:09:34.816000",
        "end": "0:09:35.392000",
        "speaker": "0"
    },
    {
        "start": "0:09:35.456000",
        "end": "0:09:37.184000",
        "speaker": "0"
    },
    {
        "start": "0:09:37.984000",
        "end": "0:09:39.072000",
        "speaker": "0"
    },
    {
        "start": "0:09:39.104000",
        "end": "0:09:40.704000",
        "speaker": "0"
    },
    {
        "start": "0:09:40.736000",
        "end": "0:09:41.376000",
        "speaker": "0"
    },
    {
        "start": "0:09:41.408000",
        "end": "0:09:42.112000",
        "speaker": "0"
    },
    {
        "start": "0:09:42.176000",
        "end": "0:09:43.456000",
        "speaker": "0"
    },
    {
        "start": "0:09:43.744000",
        "end": "0:09:45.248000",
        "speaker": "0"
    },
    {
        "start": "0:09:45.792000",
        "end": "0:09:47.936000",
        "speaker": "0"
    },
    {
        "start": "0:09:49.664000",
        "end": "0:09:51.872000",
        "speaker": "0"
    },
    {
        "start": "0:09:52.288000",
        "end": "0:09:53.216000",
        "speaker": "0"
    },
    {
        "start": "0:09:53.280000",
        "end": "0:09:53.856000",
        "speaker": "0"
    },
    {
        "start": "0:09:54.336000",
        "end": "0:09:55.680000",
        "speaker": "0"
    },
    {
        "start": "0:09:56.256000",
        "end": "0:09:57.088000",
        "speaker": "0"
    },
    {
        "start": "0:09:59.072000",
        "end": "0:09:59.648000",
        "speaker": "0"
    },
    {
        "start": "0:09:59.904000",
        "end": "0:10:01.152000",
        "speaker": "0"
    },
    {
        "start": "0:10:01.216000",
        "end": "0:10:02.688000",
        "speaker": "0"
    },
    {
        "start": "0:10:02.880000",
        "end": "0:10:04",
        "speaker": "0"
    },
    {
        "start": "0:10:04.640000",
        "end": "0:10:05.632000",
        "speaker": "0"
    },
    {
        "start": "0:10:07.776000",
        "end": "0:10:08.672000",
        "speaker": "0"
    },
    {
        "start": "0:10:08.704000",
        "end": "0:10:10.656000",
        "speaker": "0"
    },
    {
        "start": "0:10:11.040000",
        "end": "0:10:12.416000",
        "speaker": "0"
    },
    {
        "start": "0:10:12.480000",
        "end": "0:10:12.992000",
        "speaker": "0"
    },
    {
        "start": "0:10:13.792000",
        "end": "0:10:14.656000",
        "speaker": "0"
    },
    {
        "start": "0:10:14.976000",
        "end": "0:10:16.928000",
        "speaker": "0"
    },
    {
        "start": "0:10:16.960000",
        "end": "0:10:17.952000",
        "speaker": "0"
    },
    {
        "start": "0:10:18.880000",
        "end": "0:10:20.576000",
        "speaker": "0"
    },
    {
        "start": "0:10:20.928000",
        "end": "0:10:22.176000",
        "speaker": "0"
    },
    {
        "start": "0:10:22.496000",
        "end": "0:10:24.128000",
        "speaker": "0"
    },
    {
        "start": "0:10:25.120000",
        "end": "0:10:26.272000",
        "speaker": "0"
    },
    {
        "start": "0:10:26.336000",
        "end": "0:10:27.392000",
        "speaker": "0"
    },
    {
        "start": "0:10:27.424000",
        "end": "0:10:28.896000",
        "speaker": "0"
    },
    {
        "start": "0:10:28.992000",
        "end": "0:10:29.920000",
        "speaker": "0"
    },
    {
        "start": "0:10:30.432000",
        "end": "0:10:31.040000",
        "speaker": "0"
    },
    {
        "start": "0:10:32.480000",
        "end": "0:10:33.024000",
        "speaker": "0"
    },
    {
        "start": "0:10:33.504000",
        "end": "0:10:34.816000",
        "speaker": "0"
    },
    {
        "start": "0:10:36.352000",
        "end": "0:10:36.960000",
        "speaker": "0"
    },
    {
        "start": "0:10:36.992000",
        "end": "0:10:37.504000",
        "speaker": "0"
    },
    {
        "start": "0:10:39.200000",
        "end": "0:10:40.288000",
        "speaker": "0"
    },
    {
        "start": "0:10:40.736000",
        "end": "0:10:41.408000",
        "speaker": "0"
    },
    {
        "start": "0:10:41.440000",
        "end": "0:10:42.208000",
        "speaker": "0"
    },
    {
        "start": "0:10:42.240000",
        "end": "0:10:43.520000",
        "speaker": "0"
    },
    {
        "start": "0:10:45.920000",
        "end": "0:10:46.496000",
        "speaker": "0"
    },
    {
        "start": "0:10:46.560000",
        "end": "0:10:47.072000",
        "speaker": "0"
    },
    {
        "start": "0:10:47.968000",
        "end": "0:10:49.472000",
        "speaker": "0"
    },
    {
        "start": "0:10:50.784000",
        "end": "0:10:52.448000",
        "speaker": "0"
    },
    {
        "start": "0:10:52.896000",
        "end": "0:10:53.440000",
        "speaker": "0"
    },
    {
        "start": "0:10:54.048000",
        "end": "0:10:55.136000",
        "speaker": "0"
    },
    {
        "start": "0:10:55.264000",
        "end": "0:10:56.032000",
        "speaker": "0"
    },
    {
        "start": "0:10:57.184000",
        "end": "0:10:58.304000",
        "speaker": "0"
    },
    {
        "start": "0:11:00",
        "end": "0:11:01.280000",
        "speaker": "0"
    },
    {
        "start": "0:11:02.624000",
        "end": "0:11:03.776000",
        "speaker": "0"
    },
    {
        "start": "0:11:07.328000",
        "end": "0:11:08.672000",
        "speaker": "0"
    },
    {
        "start": "0:11:11.552000",
        "end": "0:11:12.640000",
        "speaker": "0"
    },
    {
        "start": "0:11:12.672000",
        "end": "0:11:13.696000",
        "speaker": "0"
    },
    {
        "start": "0:11:13.728000",
        "end": "0:11:14.720000",
        "speaker": "0"
    },
    {
        "start": "0:11:15.616000",
        "end": "0:11:16.160000",
        "speaker": "0"
    },
    {
        "start": "0:11:16.896000",
        "end": "0:11:17.600000",
        "speaker": "0"
    },
    {
        "start": "0:11:17.952000",
        "end": "0:11:18.688000",
        "speaker": "0"
    },
    {
        "start": "0:11:18.720000",
        "end": "0:11:19.392000",
        "speaker": "0"
    }
]